hok/__init__.py
hok/version.py
hok/common/__init__.py
hok/common/camp.py
hok/common/gamecore_client.py
hok/common/log.py
hok/common/server_process.py
hok/hok1v1/__init__.py
hok/hok1v1/agent.py
hok/hok1v1/config.dat
hok/hok1v1/config.json
hok/hok1v1/default_hero_config.json
hok/hok1v1/env1v1.py
hok/hok1v1/hero_config.py
hok/hok1v1/server.py
hok/hok1v1/server_delay.py
hok/hok1v1/version.py
hok/hok1v1/lib/__init__.py
hok/hok1v1/lib/interface.cpython-36m-x86_64-linux-gnu.so
hok/hok1v1/lib/interface.cpython-37m-x86_64-linux-gnu.so
hok/hok1v1/lib/interface.cpython-38-x86_64-linux-gnu.so
hok/hok1v1/lib/interface.cpython-39-x86_64-linux-gnu.so
hok/hok1v1/unit_test/__init__.py
hok/hok1v1/unit_test/config.json
hok/hok1v1/unit_test/test_env.py
hok/hok3v3/__init__.py
hok/hok3v3/action_space.py
hok/hok3v3/action_space_test.py
hok/hok3v3/config.dat
hok/hok3v3/default_hero_config.json
hok/hok3v3/env.py
hok/hok3v3/hero_config.py
hok/hok3v3/reward.py
hok/hok3v3/server.py
hok/hok3v3/lib/__init__.py
hok/hok3v3/lib/lib3v3.cpython-36m-x86_64-linux-gnu.so
hok/hok3v3/lib/lib3v3.cpython-37m-x86_64-linux-gnu.so
hok/hok3v3/lib/lib3v3.cpython-38-x86_64-linux-gnu.so
hok/hok3v3/lib/lib3v3.cpython-39-x86_64-linux-gnu.so
hok/hok3v3/lib/libinterface.so
hok/hok3v3/unit_test/__init__.py
hok/hok3v3/unit_test/test_env.py
hok-2.0.4.dist-info/METADATA
hok-2.0.4.dist-info/WHEEL
hok-2.0.4.dist-info/top_level.txt
hok-2.0.4.dist-info/RECORD
